<?xml version="1.0" encoding="UTF-8"?>
<spawns>
    <spawn_map map_id="300200000">
        <!-- Amethyst -->
        <spawn npc_id="400302">
            <spot x="300.717" y="429.704" z="93.4617"/>
            <spot x="256.169" y="399.106" z="91.8902"/>
            <spot x="323.971" y="415.126" z="91.5714"/>
        </spawn>
        <!-- Crystal -->
        <spawn npc_id="400303">
            <spot x="367.291" y="376.065" z="96.5474"/>
            <spot x="382.143" y="316.132" z="88.3009"/>
            <spot x="386.906" y="282.663" z="93.3255"/>
        </spawn>
        <!-- Rose Quartz -->
        <spawn npc_id="400301">
            <spot x="326.17" y="322.972" z="89.5445"/>
            <spot x="347.481" y="323.342" z="87.7529"/>
            <spot x="326.895" y="352.164" z="90.0598"/>
        </spawn>
        <!-- Silver -->
        <spawn npc_id="400101">
            <spot x="246.437" y="364.112" z="138.17"/>
            <spot x="213.334" y="359.185" z="140.225"/>
            <spot x="212.621" y="350.651" z="142.453"/>
        </spawn>
        <!-- Iron -->
        <spawn npc_id="400202">
            <spot x="69.5883" y="93.2732" z="139.912"/>
            <spot x="86.3678" y="96.1942" z="140.483"/>
            <spot x="78.9733" y="126.446" z="141.332"/>
            <spot x="100.602" y="113.529" z="139.906"/>
            <spot x="93.4669" y="83.3656" z="143.515"/>
        </spawn>
    </spawn_map>
</spawns>
